{
	"actor": {
		"displayName": "Ygritte",
		"favoritesCount": -1,
		"followersCount": -1,
		"friendsCount": -1,
		"id": "id:twitter.com:735369652956766208",
		"image": "https://pbs.twimg.com/profile_images/735370259566329856/3mxqMJEq_normal.jpg",
		"languages": [
			"en"
		],
		"link": "http://www.twitter.com/ygritteygritte",
		"links": [
			{
				"href": null,
				"rel": "me"
			}
		],
		"listedCount": -1,
		"objectType": "person",
		"postedTime": "2016-05-25T07:19:22.568Z",
		"preferredUsername": "ygritteygritte",
		"statusesCount": -1,
		"summary": null,
		"twitterTimeZone": null,
		"utcOffset": null,
		"verified": false
	},
	"body": "This is still the best cat https://t.co/Qhq3W7v0BP",
	"display_text_range": [
		0,
		26
	],
	"favoritesCount": 0,
	"generator": {
		"displayName": "Twitter Web Client",
		"link": "http://twitter.com"
	},
	"id": "tag:search.twitter.com,2005:758833194632224768",
	"link": "http://twitter.com/ygritteygritte/statuses/758833194632224768",
	"object": {
		"id": "object:search.twitter.com,2005:758833194632224768",
		"link": "http://twitter.com/ygritteygritte/statuses/758833194632224768",
		"objectType": "note",
		"postedTime": "2016-07-29T01:15:06.000Z",
		"summary": "This is still the best cat https://t.co/Qhq3W7v0BP"
	},
	"objectType": "activity",
	"postedTime": "2016-07-29T01:15:06.000Z",
	"provider": {
		"displayName": "Twitter",
		"link": "http://www.twitter.com",
		"objectType": "service"
	},
	"retweetCount": 0,
	"twitter_entities": {
		"hashtags": [
		],
		"symbols": [
		],
		"urls": [
			{
				"display_url": "twitter.com/ygritteygritte…",
				"expanded_url": "https://twitter.com/ygritteygritte/status/758833133185699840",
				"indices": [
					27,
					50
				],
				"url": "https://t.co/Qhq3W7v0BP"
			}
		],
		"user_mentions": [
		]
	},
	"twitter_filter_level": "low",
	"twitter_lang": "en",
	"twitter_quoted_status": {
		"actor": {
			"displayName": "Ygritte",
			"favoritesCount": -1,
			"followersCount": -1,
			"friendsCount": -1,
			"id": "id:twitter.com:735369652956766208",
			"image": "https://pbs.twimg.com/profile_images/735370259566329856/3mxqMJEq_normal.jpg",
			"languages": [
				"en"
			],
			"link": "http://www.twitter.com/ygritteygritte",
			"links": [
				{
					"href": null,
					"rel": "me"
				}
			],
			"listedCount": -1,
			"objectType": "person",
			"postedTime": "2016-05-25T07:19:22.568Z",
			"preferredUsername": "ygritteygritte",
			"statusesCount": -1,
			"summary": null,
			"twitterTimeZone": null,
			"utcOffset": null,
			"verified": false
		},
		"body": "@maliceyang this cat is the best cat i've ever seen",
		"display_text_range": [
			12,
			51
		],
		"favoritesCount": 0,
		"generator": {
			"displayName": "Twitter Web Client",
			"link": "http://twitter.com"
		},
		"id": "tag:search.twitter.com,2005:758833133185699840",
		"inReplyTo": {
			"link": "http://twitter.com/maliceyang/statuses/756633492579028992"
		},
		"link": "http://twitter.com/ygritteygritte/statuses/758833133185699840",
		"object": {
			"id": "object:search.twitter.com,2005:758833133185699840",
			"link": "http://twitter.com/ygritteygritte/statuses/758833133185699840",
			"objectType": "note",
			"postedTime": "2016-07-29T01:14:52.000Z",
			"summary": "@maliceyang this cat is the best cat i've ever seen"
		},
		"objectType": "activity",
		"postedTime": "2016-07-29T01:14:52.000Z",
		"provider": {
			"displayName": "Twitter",
			"link": "http://www.twitter.com",
			"objectType": "service"
		},
		"twitter_entities": {
			"hashtags": [
			],
			"symbols": [
			],
			"urls": [
			],
			"user_mentions": [
				{
					"id": 21015627,
					"id_str": "21015627",
					"indices": [
						0,
						11
					],
					"name": "Alice Yang",
					"screen_name": "maliceyang"
				}
			]
		},
		"twitter_filter_level": "low",
		"twitter_lang": "en",
		"verb": "post"
	},
	"verb": "post"
}